nn_acc_ss/AHB-to-APB-Bridge/APB_Interface.v
module APB_Interface (
    input  wire        Pwrite,
    input  wire        Penable,
    input  wire [2:0]  Pselx,
    input  wire [31:0] Paddr,
    input  wire [31:0] Pwdata,

    output wire        Pwriteout,
    output wire        Penableout,
    output wire [2:0]  Pselxout,
    output wire [31:0] Paddrout,
    output wire [31:0] Pwdataout,

    output reg  [31:0] Prdata
);

    // ------------------------------------------------
    // Pass-through APB signals
    // ------------------------------------------------
    assign Pwriteout  = Pwrite;
    assign Penableout = Penable;
    assign Pselxout   = Pselx;
    assign Paddrout   = Paddr;
    assign Pwdataout  = Pwdata;

    // ------------------------------------------------
    // Simple APB read data logic
    // ------------------------------------------------
    always @(*) begin
        if (!Pwrite && Penable && (Pselx != 3'b000))
            Prdata = {24'b0, Paddr[7:0]};  // example readable data
        else
            Prdata = 32'b0;
    end

endmodule

nn_acc_ss/AHB-to-APB-Bridge/APB_Controller.v
module APB_FSM_Controller (
    input  wire        Hclk,
    input  wire        Hresetn,

    // From AHB slave interface
    input  wire        valid,
    input  wire        Hwrite,
    input  wire        Hwritereg,
    input  wire [31:0] Haddr,
    input  wire [31:0] Haddr1,
    input  wire [31:0] Haddr2,
    input  wire [31:0] Hwdata1,
    input  wire [31:0] Hwdata2,
    input  wire [2:0]  tempselx,

    // APB outputs
    output reg         Pwrite,
    output reg         Penable,
    output reg [2:0]   Pselx,
    output reg [31:0]  Paddr,
    output reg [31:0]  Pwdata,

    // Back to AHB
    output reg         Hreadyout
);

    // ------------------------------------------------
    // FSM state encoding
    // ------------------------------------------------
    localparam ST_IDLE     = 3'b000;
    localparam ST_WWAIT    = 3'b001;
    localparam ST_READ     = 3'b010;
    localparam ST_WRITE    = 3'b011;
    localparam ST_WRITEP   = 3'b100;
    localparam ST_RENABLE  = 3'b101;
    localparam ST_WENABLE  = 3'b110;
    localparam ST_WENABLEP = 3'b111;

    reg [2:0] PRESENT_STATE, NEXT_STATE;

    // ------------------------------------------------
    // Present state logic
    // ------------------------------------------------
    always @(posedge Hclk) begin
        if (!Hresetn)
            PRESENT_STATE <= ST_IDLE;
        else
            PRESENT_STATE <= NEXT_STATE;
    end

    // ------------------------------------------------
    // Next state logic
    // ------------------------------------------------
    always @(*) begin
        case (PRESENT_STATE)

            ST_IDLE:
                if (!valid)
                    NEXT_STATE = ST_IDLE;
                else if (valid && Hwrite)
                    NEXT_STATE = ST_WWAIT;
                else
                    NEXT_STATE = ST_READ;

            ST_WWAIT:
                if (!valid)
                    NEXT_STATE = ST_WRITE;
                else
                    NEXT_STATE = ST_WRITEP;

            ST_READ:
                NEXT_STATE = ST_RENABLE;

            ST_WRITE:
                if (!valid)
                    NEXT_STATE = ST_WENABLE;
                else
                    NEXT_STATE = ST_WENABLEP;

            ST_WRITEP:
                NEXT_STATE = ST_WENABLEP;

            ST_RENABLE:
                if (!valid)
                    NEXT_STATE = ST_IDLE;
                else if (valid && Hwrite)
                    NEXT_STATE = ST_WWAIT;
                else
                    NEXT_STATE = ST_READ;

            ST_WENABLE:
                if (!valid)
                    NEXT_STATE = ST_IDLE;
                else if (valid && Hwrite)
                    NEXT_STATE = ST_WWAIT;
                else
                    NEXT_STATE = ST_READ;

            ST_WENABLEP:
                if (!valid && Hwritereg)
                    NEXT_STATE = ST_WRITE;
                else if (valid && Hwritereg)
                    NEXT_STATE = ST_WRITEP;
                else
                    NEXT_STATE = ST_READ;

            default:
                NEXT_STATE = ST_IDLE;
        endcase
    end

    // ------------------------------------------------
    // Output combinational logic (LATCH-FREE)
    // ------------------------------------------------
    reg        Pwrite_temp, Penable_temp, Hreadyout_temp;
    reg [2:0]  Pselx_temp;
    reg [31:0] Paddr_temp, Pwdata_temp;

    always @(*) begin
        // ---------- DEFAULTS (CRITICAL) ----------
        Paddr_temp     = Paddr;
        Pwdata_temp    = Pwdata;
        Pwrite_temp    = 1'b0;
        Pselx_temp     = 3'b000;
        Penable_temp   = 1'b0;
        Hreadyout_temp = 1'b1;

        case (PRESENT_STATE)

            ST_IDLE: begin
                if (valid && !Hwrite) begin
                    Paddr_temp     = Haddr1;
                    Pwrite_temp    = 1'b0;
                    Pselx_temp     = tempselx;
                    Hreadyout_temp = 1'b0;
                end
                else if (valid && Hwrite) begin
                    Hreadyout_temp = 1'b1;
                end
            end

            ST_WWAIT: begin
                Paddr_temp     = Haddr1;
                Pwdata_temp    = Hwdata1;
                Pwrite_temp    = 1'b1;
                Pselx_temp     = tempselx;
                Hreadyout_temp = 1'b0;
            end

            ST_READ: begin
                Penable_temp   = 1'b1;
                Hreadyout_temp = 1'b1;
            end

            ST_WRITE: begin
                Penable_temp   = 1'b1;
                Hreadyout_temp = 1'b1;
            end

            ST_WRITEP: begin
                Penable_temp   = 1'b1;
                Hreadyout_temp = 1'b1;
            end

            ST_RENABLE: begin
                if (valid && !Hwrite) begin
                    Paddr_temp     = Haddr1;
                    Pwrite_temp    = 1'b0;
                    Pselx_temp     = tempselx;
                    Hreadyout_temp = 1'b0;
                end
                else if (valid && Hwrite) begin
                    Hreadyout_temp = 1'b1;
                end
            end

            ST_WENABLE: begin
                Hreadyout_temp = 1'b1;
            end

            ST_WENABLEP: begin
                Paddr_temp     = Haddr2;
                Pwdata_temp    = Hwdata2;
                Pwrite_temp    = 1'b1;
                Pselx_temp     = tempselx;
                Hreadyout_temp = 1'b0;
            end

        endcase
    end

    // ------------------------------------------------
    // Output registers
    // ------------------------------------------------
    always @(posedge Hclk) begin
        if (!Hresetn) begin
            Paddr     <= 32'b0;
            Pwdata    <= 32'b0;
            Pwrite    <= 1'b0;
            Pselx     <= 3'b000;
            Penable   <= 1'b0;
            Hreadyout <= 1'b1;
        end
        else begin
            Paddr     <= Paddr_temp;
            Pwdata    <= Pwdata_temp;
            Pwrite    <= Pwrite_temp;
            Pselx     <= Pselx_temp;
            Penable   <= Penable_temp;
            Hreadyout <= Hreadyout_temp;
        end
    end

endmodule

nn_acc_ss/AHB-to-APB-Bridge/AHB_Slave_Interface.v
module AHB_slave_interface (
    input  wire        Hclk,
    input  wire        Hresetn,

    // AHB inputs
    input  wire        Hwrite,
    input  wire        Hreadyin,
    input  wire [1:0]  Htrans,
    input  wire [31:0] Haddr,
    input  wire [31:0] Hwdata,

    // Peripheral read data
    input  wire [31:0] Prdata,

    // Outputs
    output reg         valid,
    output reg [31:0]  Haddr1,
    output reg [31:0]  Haddr2,
    output reg [31:0]  Hwdata1,
    output reg [31:0]  Hwdata2,
    output wire [31:0] Hrdata,
    output reg         Hwritereg,
    output reg [2:0]   tempselx,
    output wire [1:0]  Hresp
);

    // ------------------------------------------------
    // Address pipeline
    // ------------------------------------------------
    always @(posedge Hclk) begin
        if (!Hresetn) begin
            Haddr1 <= 32'b0;
            Haddr2 <= 32'b0;
        end else begin
            Haddr1 <= Haddr;
            Haddr2 <= Haddr1;
        end
    end

    // ------------------------------------------------
    // Write data pipeline
    // ------------------------------------------------
    always @(posedge Hclk) begin
        if (!Hresetn) begin
            Hwdata1 <= 32'b0;
            Hwdata2 <= 32'b0;
        end else begin
            Hwdata1 <= Hwdata;
            Hwdata2 <= Hwdata1;
        end
    end

    // ------------------------------------------------
    // Write control pipeline
    // ------------------------------------------------
    always @(posedge Hclk) begin
        if (!Hresetn)
            Hwritereg <= 1'b0;
        else
            Hwritereg <= Hwrite;
    end

    // ------------------------------------------------
    // VALID generation (registered  AHB correct)
    // ------------------------------------------------
    always @(posedge Hclk) begin
        if (!Hresetn)
            valid <= 1'b0;
        else
            valid <= Hreadyin &&
                     (Haddr >= 32'h8000_0000 && Haddr < 32'h8C00_0000) &&
                     (Htrans == 2'b10 || Htrans == 2'b11);
    end

    // ------------------------------------------------
    // Slave select decode
    // ------------------------------------------------
    always @(*) begin
        tempselx = 3'b000;

        if (Haddr >= 32'h8000_0000 && Haddr < 32'h8400_0000)
            tempselx = 3'b001;
        else if (Haddr >= 32'h8400_0000 && Haddr < 32'h8800_0000)
            tempselx = 3'b010;
        else if (Haddr >= 32'h8800_0000 && Haddr < 32'h8C00_0000)
            tempselx = 3'b100;
    end

    // ------------------------------------------------
    // Read data & response
    // ------------------------------------------------
    assign Hrdata = Prdata;   // AHB read data
    assign Hresp  = 2'b00;    // OKAY response

endmodule

nn_acc_ss/AHB-to-APB-Bridge/bridge_top.v
module Bridge_Top (
    input  wire        Hclk,
    input  wire        Hresetn,

    // AHB side
    input  wire        Hwrite,
    input  wire        Hreadyin,
    input  wire [1:0]  Htrans,
    input  wire [31:0] Haddr,
    input  wire [31:0] Hwdata,

    output wire        Hreadyout,
    output wire [1:0]  Hresp,
    output wire [31:0] Hrdata,

    // APB side
    output wire        Pwrite,
    output wire        Penable,
    output wire [2:0]  Pselx,
    output wire [31:0] Paddr,
    output wire [31:0] Pwdata
);

    // ------------------------------------------------
    // Internal wires
    // ------------------------------------------------
    wire        valid;
    wire [31:0] Haddr1, Haddr2;
    wire [31:0] Hwdata1, Hwdata2;
    wire        Hwritereg;
    wire [2:0]  tempselx;
    wire [31:0] Prdata;

    // ------------------------------------------------
    // AHB Slave Interface
    // ------------------------------------------------
    AHB_slave_interface u_ahb_slave (
        .Hclk      (Hclk),
        .Hresetn   (Hresetn),
        .Hwrite    (Hwrite),
        .Hreadyin  (Hreadyin),
        .Htrans    (Htrans),
        .Haddr     (Haddr),
        .Hwdata    (Hwdata),
        .Prdata    (Prdata),
        .valid     (valid),
        .Haddr1    (Haddr1),
        .Haddr2    (Haddr2),
        .Hwdata1   (Hwdata1),
        .Hwdata2   (Hwdata2),
        .Hrdata    (Hrdata),
        .Hwritereg (Hwritereg),
        .tempselx  (tempselx),
        .Hresp     (Hresp)
    );

    // ------------------------------------------------
    // APB FSM Controller
    // ------------------------------------------------
    APB_FSM_Controller u_apb_fsm (
        .Hclk      (Hclk),
        .Hresetn   (Hresetn),
        .valid     (valid),
        .Hwrite    (Hwrite),
        .Hwritereg (Hwritereg),
        .Haddr     (Haddr),
        .Haddr1    (Haddr1),
        .Haddr2    (Haddr2),
        .Hwdata1   (Hwdata1),
        .Hwdata2   (Hwdata2),
        .tempselx  (tempselx),
        .Pwrite    (Pwrite),
        .Penable   (Penable),
        .Pselx     (Pselx),
        .Paddr     (Paddr),
        .Pwdata    (Pwdata),
        .Hreadyout (Hreadyout)
    );

    // ------------------------------------------------
    // APB Peripheral Interface
    // ------------------------------------------------
    APB_Interface u_apb_if (
        .Pwrite    (Pwrite),
        .Penable   (Penable),
        .Pselx     (Pselx),
        .Paddr     (Paddr),
        .Pwdata    (Pwdata),
        .Pwriteout (),
        .Penableout(),
        .Pselxout  (),
        .Paddrout  (),
        .Pwdataout (),
        .Prdata    (Prdata)
    );

endmodule

nn_acc_ss/AHB-to-APB-Bridge/tb_bridge_top.v
`timescale 1ns/1ps

module tb_bridge_top;

    reg         Hclk;
    reg         Hresetn;
    reg         Hwrite;
    reg         Hreadyin;
    reg [1:0]   Htrans;
    reg [31:0]  Haddr;
    reg [31:0]  Hwdata;

    wire        Hreadyout;
    wire [1:0]  Hresp;
    wire [31:0] Hrdata;

    wire        Pwrite;
    wire        Penable;
    wire [2:0]  Pselx;
    wire [31:0] Paddr;
    wire [31:0] Pwdata;

    // ----------------------------------------
    // DUT
    // ----------------------------------------
    Bridge_Top dut (
        .Hclk      (Hclk),
        .Hresetn   (Hresetn),
        .Hwrite    (Hwrite),
        .Hreadyin  (Hreadyin),
        .Htrans    (Htrans),
        .Haddr     (Haddr),
        .Hwdata    (Hwdata),
        .Hreadyout (Hreadyout),
        .Hresp     (Hresp),
        .Hrdata    (Hrdata),
        .Pwrite    (Pwrite),
        .Penable   (Penable),
        .Pselx     (Pselx),
        .Paddr     (Paddr),
        .Pwdata    (Pwdata)
    );

    // ----------------------------------------
    // Clock generation
    // ----------------------------------------
    always #5 Hclk = ~Hclk;

    // ----------------------------------------
    // Stimulus
    // ----------------------------------------
    initial begin
        // init
        Hclk     = 0;
        Hresetn  = 0;
        Hwrite   = 0;
        Hreadyin = 1;
        Htrans   = 2'b00;
        Haddr    = 0;
        Hwdata   = 0;

        // reset
        #20;
        Hresetn = 1;

        // -------------------------------
        // AHB WRITE
        // -------------------------------
        @(posedge Hclk);
        Hwrite = 1;
        Htrans = 2'b10;               // NONSEQ
        Haddr  = 32'h8000_0004;
        Hwdata = 32'hDEADBEEF;

        @(posedge Hclk);
        Htrans = 2'b00;               // IDLE

        // -------------------------------
        // AHB READ
        // -------------------------------
        repeat(2) @(posedge Hclk);

        Hwrite = 0;
        Htrans = 2'b10;               // NONSEQ
        Haddr  = 32'h8000_0004;

        @(posedge Hclk);
        Htrans = 2'b00;

        // let it run
        repeat(10) @(posedge Hclk);

        $finish;
    end
    initial begin
    $dumpfile("bridge.vcd");
    $dumpvars(0, tb_bridge_top);
end

endmodule

nn_acc_ss/AHB-to-APB-Bridge/bridge.vcd
$date
	Fri Dec 19 15:17:56 2025
$end
$version
	Icarus Verilog
$end
$timescale
	1ps
$end
$scope module tb_bridge_top $end
$var wire 2 ! Hresp [1:0] $end
$var wire 1 " Pwrite $end
$var wire 32 # Pwdata [31:0] $end
$var wire 3 $ Pselx [2:0] $end
$var wire 1 % Penable $end
$var wire 32 & Paddr [31:0] $end
$var wire 1 ' Hreadyout $end
$var wire 32 ( Hrdata [31:0] $end
$var reg 32 ) Haddr [31:0] $end
$var reg 1 * Hclk $end
$var reg 1 + Hreadyin $end
$var reg 1 , Hresetn $end
$var reg 2 - Htrans [1:0] $end
$var reg 32 . Hwdata [31:0] $end
$var reg 1 / Hwrite $end
$scope module dut $end
$var wire 32 0 Haddr [31:0] $end
$var wire 1 * Hclk $end
$var wire 1 + Hreadyin $end
$var wire 1 , Hresetn $end
$var wire 2 1 Hresp [1:0] $end
$var wire 2 2 Htrans [1:0] $end
$var wire 32 3 Hwdata [31:0] $end
$var wire 1 / Hwrite $end
$var wire 1 4 valid $end
$var wire 3 5 tempselx [2:0] $end
$var wire 1 " Pwrite $end
$var wire 32 6 Pwdata [31:0] $end
$var wire 3 7 Pselx [2:0] $end
$var wire 32 8 Prdata [31:0] $end
$var wire 1 % Penable $end
$var wire 32 9 Paddr [31:0] $end
$var wire 1 : Hwritereg $end
$var wire 32 ; Hwdata2 [31:0] $end
$var wire 32 < Hwdata1 [31:0] $end
$var wire 1 ' Hreadyout $end
$var wire 32 = Hrdata [31:0] $end
$var wire 32 > Haddr2 [31:0] $end
$var wire 32 ? Haddr1 [31:0] $end
$scope module u_ahb_slave $end
$var wire 32 @ Haddr [31:0] $end
$var wire 1 * Hclk $end
$var wire 32 A Hrdata [31:0] $end
$var wire 1 + Hreadyin $end
$var wire 1 , Hresetn $end
$var wire 2 B Hresp [1:0] $end
$var wire 2 C Htrans [1:0] $end
$var wire 32 D Hwdata [31:0] $end
$var wire 1 / Hwrite $end
$var wire 32 E Prdata [31:0] $end
$var reg 32 F Haddr1 [31:0] $end
$var reg 32 G Haddr2 [31:0] $end
$var reg 32 H Hwdata1 [31:0] $end
$var reg 32 I Hwdata2 [31:0] $end
$var reg 1 : Hwritereg $end
$var reg 3 J tempselx [2:0] $end
$var reg 1 4 valid $end
$upscope $end
$scope module u_apb_fsm $end
$var wire 32 K Haddr [31:0] $end
$var wire 32 L Haddr1 [31:0] $end
$var wire 32 M Haddr2 [31:0] $end
$var wire 1 * Hclk $end
$var wire 1 , Hresetn $end
$var wire 32 N Hwdata1 [31:0] $end
$var wire 32 O Hwdata2 [31:0] $end
$var wire 1 / Hwrite $end
$var wire 1 : Hwritereg $end
$var wire 3 P tempselx [2:0] $end
$var wire 1 4 valid $end
$var parameter 3 Q ST_IDLE $end
$var parameter 3 R ST_READ $end
$var parameter 3 S ST_RENABLE $end
$var parameter 3 T ST_WENABLE $end
$var parameter 3 U ST_WENABLEP $end
$var parameter 3 V ST_WRITE $end
$var parameter 3 W ST_WRITEP $end
$var parameter 3 X ST_WWAIT $end
$var reg 1 ' Hreadyout $end
$var reg 1 Y Hreadyout_temp $end
$var reg 3 Z NEXT_STATE [2:0] $end
$var reg 3 [ PRESENT_STATE [2:0] $end
$var reg 32 \ Paddr [31:0] $end
$var reg 32 ] Paddr_temp [31:0] $end
$var reg 1 % Penable $end
$var reg 1 ^ Penable_temp $end
$var reg 3 _ Pselx [2:0] $end
$var reg 3 ` Pselx_temp [2:0] $end
$var reg 32 a Pwdata [31:0] $end
$var reg 32 b Pwdata_temp [31:0] $end
$var reg 1 " Pwrite $end
$var reg 1 c Pwrite_temp $end
$upscope $end
$scope module u_apb_if $end
$var wire 32 d Paddr [31:0] $end
$var wire 32 e Paddrout [31:0] $end
$var wire 1 % Penable $end
$var wire 1 f Penableout $end
$var wire 3 g Pselx [2:0] $end
$var wire 3 h Pselxout [2:0] $end
$var wire 32 i Pwdata [31:0] $end
$var wire 32 j Pwdataout [31:0] $end
$var wire 1 " Pwrite $end
$var wire 1 k Pwriteout $end
$var reg 32 l Prdata [31:0] $end
$upscope $end
$upscope $end
$upscope $end
$enddefinitions $end
$comment Show the parameter values. $end
$dumpall
b1 X
b100 W
b11 V
b111 U
b110 T
b101 S
b10 R
b0 Q
$end
#0
$dumpvars
bx l
xk
bx j
bx i
bx h
bx g
xf
bx e
bx d
0c
bx b
bx a
b0 `
bx _
0^
bx ]
bx \
bx [
b0 Z
1Y
b0 P
bx O
bx N
bx M
bx L
b0 K
b0 J
bx I
bx H
bx G
bx F
bx E
b0 D
b0 C
b0 B
bx A
b0 @
bx ?
bx >
bx =
bx <
bx ;
x:
bx 9
bx 8
bx 7
bx 6
b0 5
x4
b0 3
b0 2
b0 1
b0 0
0/
b0 .
b0 -
0,
1+
0*
b0 )
bx (
x'
bx &
x%
bx $
bx #
x"
b0 !
$end
#5000
b0 b
b0 ]
b0 (
b0 =
b0 A
b0 8
b0 E
b0 l
b0 >
b0 G
b0 M
b0 ?
b0 F
b0 L
b0 ;
b0 I
b0 O
b0 <
b0 H
b0 N
0:
04
b0 [
1'
0f
0%
b0 h
b0 $
b0 7
b0 _
b0 g
0k
0"
b0 j
b0 #
b0 6
b0 a
b0 i
b0 e
b0 &
b0 9
b0 \
b0 d
1*
#10000
0*
#15000
1*
#20000
0*
1,
#25000
b1 Z
b10000000000000000000000000000100 ?
b10000000000000000000000000000100 F
b10000000000000000000000000000100 L
b11011110101011011011111011101111 <
b11011110101011011011111011101111 H
b11011110101011011011111011101111 N
1:
14
b1 5
b1 J
b1 P
b11011110101011011011111011101111 .
b11011110101011011011111011101111 3
b11011110101011011011111011101111 D
b10000000000000000000000000000100 )
b10000000000000000000000000000100 0
b10000000000000000000000000000100 @
b10000000000000000000000000000100 K
b10 -
b10 2
b10 C
1/
1*
#30000
0*
#35000
b100 Z
0Y
b1 `
1c
b11011110101011011011111011101111 b
b10000000000000000000000000000100 ]
b1 [
b11011110101011011011111011101111 ;
b11011110101011011011111011101111 I
b11011110101011011011111011101111 O
b10000000000000000000000000000100 >
b10000000000000000000000000000100 G
b10000000000000000000000000000100 M
b0 -
b0 2
b0 C
1*
#40000
0*
#45000
b111 Z
1^
1Y
b0 `
0c
04
b100 [
0'
b1 h
b1 $
b1 7
b1 _
b1 g
1k
1"
b11011110101011011011111011101111 j
b11011110101011011011111011101111 #
b11011110101011011011111011101111 6
b11011110101011011011111011101111 a
b11011110101011011011111011101111 i
b10000000000000000000000000000100 e
b10000000000000000000000000000100 &
b10000000000000000000000000000100 9
b10000000000000000000000000000100 \
b10000000000000000000000000000100 d
1*
#50000
0*
#55000
0Y
b1 `
1c
b11 Z
1'
1f
1%
b0 h
b0 $
b0 7
b0 _
b0 g
0k
0"
b111 [
0^
b10 -
b10 2
b10 C
0/
1*
#60000
0*
#65000
1^
1Y
b0 `
0c
b110 Z
0:
b11 [
0'
0f
0%
b1 h
b1 $
b1 7
b1 _
b1 g
1k
1"
b0 -
b0 2
b0 C
1*
#70000
0*
#75000
0^
b0 Z
1'
1f
1%
b0 h
b0 $
b0 7
b0 _
b0 g
0k
0"
b110 [
1*
#80000
0*
#85000
b0 [
0f
0%
1*
